LICENSE
README.md
pyproject.toml
eznlp/__init__.py
eznlp/config.py
eznlp/dataset.py
eznlp/metrics.py
eznlp/token.py
eznlp/vectors.py
eznlp/vocab.py
eznlp/wrapper.py
eznlp.egg-info/PKG-INFO
eznlp.egg-info/SOURCES.txt
eznlp.egg-info/dependency_links.txt
eznlp.egg-info/requires.txt
eznlp.egg-info/top_level.txt
eznlp/io/__init__.py
eznlp/io/base.py
eznlp/io/brat.py
eznlp/io/category_folder.py
eznlp/io/chip.py
eznlp/io/conll.py
eznlp/io/json.py
eznlp/io/processing.py
eznlp/io/raw_text.py
eznlp/io/src2trg.py
eznlp/io/tabular.py
eznlp/model/__init__.py
eznlp/model/bert_like.py
eznlp/model/elmo.py
eznlp/model/embedder.py
eznlp/model/encoder.py
eznlp/model/flair.py
eznlp/model/image_encoder.py
eznlp/model/masked_span_bert_like.py
eznlp/model/nested_embedder.py
eznlp/model/span_bert_like.py
eznlp/model/decoder/__init__.py
eznlp/model/decoder/base.py
eznlp/model/decoder/boundaries.py
eznlp/model/decoder/boundary_selection.py
eznlp/model/decoder/chunks.py
eznlp/model/decoder/generator.py
eznlp/model/decoder/joint_extraction.py
eznlp/model/decoder/masked_span_attr_classification.py
eznlp/model/decoder/masked_span_rel_classification.py
eznlp/model/decoder/sequence_tagging.py
eznlp/model/decoder/span_attr_classification.py
eznlp/model/decoder/span_classification.py
eznlp/model/decoder/span_rel_classification.py
eznlp/model/decoder/specific_span_classification.py
eznlp/model/decoder/specific_span_rel_classification.py
eznlp/model/decoder/specific_span_rel_classification_unfiltered.py
eznlp/model/decoder/text_classification.py
eznlp/model/model/__init__.py
eznlp/model/model/base.py
eznlp/model/model/classifier.py
eznlp/model/model/extractor.py
eznlp/model/model/image2text.py
eznlp/model/model/masked_span_extractor.py
eznlp/model/model/specific_span_extractor.py
eznlp/model/model/text2text.py
eznlp/nn/__init__.py
eznlp/nn/functional.py
eznlp/nn/init.py
eznlp/nn/utils.py
eznlp/nn/modules/__init__.py
eznlp/nn/modules/affine_fusor.py
eznlp/nn/modules/aggregation.py
eznlp/nn/modules/attention.py
eznlp/nn/modules/block.py
eznlp/nn/modules/crf.py
eznlp/nn/modules/distance.py
eznlp/nn/modules/dropout.py
