Metadata-Version: 2.4
Name: eznlp
Version: 0.4.0
Summary: Easy Natural Language Processing
Author-email: Enwei Zhu <enwei.zhu@outlook.com>
Project-URL: homepage, https://github.com/syuoni/eznlp
Requires-Python: >=3.8
License-File: LICENSE
Requires-Dist: numpy
Requires-Dist: pandas
Requires-Dist: matplotlib
Requires-Dist: scipy
Requires-Dist: scikit-learn
Requires-Dist: torch
Requires-Dist: transformers
Requires-Dist: tokenizers
Requires-Dist: sentencepiece
Requires-Dist: nltk
Requires-Dist: truecase
Requires-Dist: hanziconv
Requires-Dist: spacy
Requires-Dist: jieba
Requires-Dist: openpyxl
Provides-Extra: dev
Requires-Dist: pytorch-crf; extra == "dev"
Requires-Dist: pytest; extra == "dev"
Requires-Dist: pre-commit; extra == "dev"
Dynamic: license-file
